{"indexes":[{"v":{"$numberInt":"2"},"key":{"_id":{"$numberInt":"1"}},"name":"_id_"},{"v":{"$numberInt":"2"},"key":{"coopId":{"$numberInt":"1"}},"name":"coopId_1","background":true},{"v":{"$numberInt":"2"},"key":{"stationName":{"$numberInt":"1"}},"name":"stationName_1","background":true},{"v":{"$numberInt":"2"},"key":{"km":{"$numberInt":"1"}},"name":"km_1","background":true},{"v":{"$numberInt":"2"},"key":{"viceVersaKM":{"$numberInt":"1"}},"name":"viceVersaKM_1","background":true},{"v":{"$numberInt":"2"},"key":{"routeId":{"$numberInt":"1"}},"name":"routeId_1","background":true},{"v":{"$numberInt":"2"},"key":{"createdAt":{"$numberInt":"1"}},"name":"createdAt_1","background":true},{"v":{"$numberInt":"2"},"key":{"updatedAt":{"$numberInt":"1"}},"name":"updatedAt_1","background":true},{"v":{"$numberInt":"2"},"key":{"rowNo":{"$numberInt":"1"}},"name":"rowNo_1","background":true}],"uuid":"fd22baa502b544f3ac835de0edfce472","collectionName":"stationrecords","type":"collection"}